verichain/__init__.py
verichain/ai_integration.py
verichain/ares_client.py
verichain/athena_client.py
verichain/canonicalization.py
verichain/cli.py
verichain/cloud_client.py
verichain/hasher.py
verichain/helios_client.py
verichain/ledger_sealed.py
verichain/log_writer.py
verichain/packager.py
verichain/recorder.py
verichain/signer.py
verichain/signer_deterministic.py
verichain-2.4.1.dist-info/METADATA
verichain-2.4.1.dist-info/WHEEL
verichain-2.4.1.dist-info/entry_points.txt
verichain-2.4.1.dist-info/top_level.txt
verichain-2.4.1.dist-info/RECORD
